{
    "song_0000": {
        "tittle": "Go with the Flow",
        "artist": "Queens of the Stone Age",
        "composer": "JOSH HOMME, NICK OLIVERI ",
        "year": 2002,
        "lyrics": [
            "She",
            "said",
            "I’ll",
            "throw",
            "myself",
            "away",
            "LYRIC",
            "They’re",
            "just",
            "photos",
            "after",
            "all",
            "LYRIC",
            "I",
            "can’t",
            "make",
            "you",
            "hang",
            "around",
            "LYRIC",
            "I",
            "can’t",
            "wash",
            "you",
            "off",
            "my",
            "skin",
            "LYRIC",
            "Outside",
            "the",
            "frame",
            "is",
            "what",
            "we’re",
            "leaving",
            "out",
            "LYRIC",
            "You",
            "won’t",
            "remember",
            "anyway",
            "LYRIC",
            "I",
            "can",
            "go",
            "with",
            "the",
            "flow",
            "LYRIC",
            "But",
            "don’t",
            "say",
            "it",
            "doesn’t",
            "matter",
            "anymore",
            "LYRIC",
            "I",
            "can",
            "go",
            "with",
            "the",
            "flow",
            "LYRIC",
            "Do",
            "you",
            "believe",
            "it",
            "in",
            "your",
            "head",
            "LYRIC",
            "It’s",
            "so",
            "safe",
            "to",
            "play",
            "along",
            "LYRIC",
            "Little",
            "soldiers",
            "in",
            "a",
            "row",
            "LYRIC",
            "Falling",
            "in",
            "and",
            "out",
            "of",
            "love",
            "LYRIC",
            "With",
            "something",
            "sweet",
            "to",
            "throw",
            "away",
            "LYRIC",
            "But",
            "I",
            "want",
            "something",
            "good",
            "to",
            "die",
            "for",
            "LYRIC",
            "To",
            "make",
            "it",
            "beautiful",
            "to",
            "live",
            "LYRIC",
            "I",
            "want",
            "a",
            "new",
            "mistake",
            "lose",
            "is",
            "more",
            "than",
            "hesitate",
            "LYRIC",
            "Do",
            "you",
            "believe",
            "it",
            "in",
            "your",
            "head",
            "LYRIC",
            "I",
            "can",
            "go",
            "with",
            "the",
            "flow",
            "LYRIC",
            "But",
            "don’t",
            "say",
            "it",
            "doesn’t",
            "matter",
            "anymore",
            "LYRIC",
            "I",
            "can",
            "go",
            "with",
            "the",
            "flow",
            "LYRIC",
            "Do",
            "you",
            "believe",
            "it",
            "in",
            "your",
            "head"
        ]
    },
    "song_0001": {
        "tittle": "Come Together",
        "artist": "The Beatles",
        "composer": "John Lennon",
        "year": 1969,
        "lyrics": [
            "Here",
            "come",
            "old",
            "flat",
            "top",
            "LYRIC",
            "He",
            "come",
            "groovin’",
            "up",
            "slowly",
            "LYRIC",
            "He",
            "got",
            "joo",
            "joo",
            "eyeballs",
            "LYRIC",
            "He",
            "one",
            "holy",
            "roller",
            "LYRIC",
            "He",
            "got",
            "hair",
            "down",
            "to",
            "his",
            "knee",
            "LYRIC",
            "Got",
            "to",
            "be",
            "a",
            "joker",
            "LYRIC",
            "He",
            "just",
            "do",
            "what",
            "he",
            "please",
            "LYRIC",
            "He",
            "wear",
            "no",
            "shoeshine",
            "LYRIC",
            "He",
            "got",
            "toe",
            "jam",
            "football",
            "LYRIC",
            "He",
            "got",
            "monkey",
            "finger",
            "LYRIC",
            "He",
            "shoot",
            "CocaCola",
            "LYRIC",
            "He",
            "say",
            "I",
            "know",
            "you",
            "you",
            "know",
            "me",
            "LYRIC",
            "One",
            "thing",
            "I",
            "can",
            "tell",
            "you",
            "is",
            "LYRIC",
            "You",
            "got",
            "to",
            "be",
            "free",
            "LYRIC",
            "Come",
            "together",
            "right",
            "now",
            "LYRIC",
            "Over",
            "me",
            "LYRIC",
            "He",
            "bad",
            "production",
            "LYRIC",
            "He",
            "got",
            "walrus",
            "gumboot",
            "LYRIC",
            "He",
            "got",
            "Ono",
            "sideboard",
            "LYRIC",
            "He",
            "one",
            "spinal",
            "cracker",
            "LYRIC",
            "He",
            "got",
            "feet",
            "down",
            "below",
            "his",
            "knee",
            "LYRIC",
            "Hold",
            "you",
            "in",
            "his",
            "armchair",
            "LYRIC",
            "You",
            "can",
            "feel",
            "his",
            "disease",
            "LYRIC",
            "Come",
            "together",
            "right",
            "now",
            "LYRIC",
            "Over",
            "me",
            "LYRIC",
            "He",
            "roller",
            "coaster",
            "LYRIC",
            "He",
            "got",
            "early",
            "warning",
            "LYRIC",
            "He",
            "got",
            "muddy",
            "water",
            "LYRIC",
            "He",
            "one",
            "Mojo",
            "filter",
            "LYRIC",
            "He",
            "say…"
        ]
    },
    "song_0002": {
        "tittle": "House of the Rising Sun",
        "artist": "The Animals",
        "composer": "Uknown",
        "year": 1964,
        "lyrics": [
            "There",
            "is",
            "a",
            "house",
            "in",
            "New",
            "Orleans",
            "LYRIC",
            "They",
            "call",
            "the",
            "Rising",
            "Sun",
            "LYRIC",
            "And",
            "it’s",
            "been",
            "the",
            "ruin",
            "of",
            "many",
            "a",
            "poor",
            "boy",
            "LYRIC",
            "And",
            "God",
            "I",
            "know",
            "I’m",
            "one",
            "LYRIC",
            "LYRIC",
            "My",
            "mother",
            "was",
            "a",
            "tailor",
            "LYRIC",
            "She",
            "sewed",
            "my",
            "new",
            "blue",
            "jeans",
            "LYRIC",
            "My",
            "father",
            "was",
            "a",
            "gamblin’",
            "man",
            "LYRIC",
            "Down",
            "in",
            "New",
            "Orleans",
            "LYRIC",
            "LYRIC",
            "Now",
            "the",
            "only",
            "thing",
            "a",
            "gambler",
            "needs",
            "LYRIC",
            "Is",
            "a",
            "suitcase",
            "and",
            "a",
            "trunk",
            "LYRIC",
            "And",
            "the",
            "only",
            "time",
            "he’s",
            "satisfied",
            "LYRIC",
            "Is",
            "when",
            "he’s",
            "on",
            "a",
            "drunk",
            "LYRIC",
            "LYRIC",
            "REPSTART",
            "Organ",
            "Solo]",
            "LYRIC",
            "LYRIC",
            "Oh",
            "mother",
            "tell",
            "your",
            "children",
            "LYRIC",
            "Not",
            "to",
            "do",
            "what",
            "I",
            "have",
            "done",
            "LYRIC",
            "Spend",
            "your",
            "lives",
            "in",
            "sin",
            "and",
            "misery",
            "LYRIC",
            "In",
            "the",
            "House",
            "of",
            "the",
            "Rising",
            "Sun",
            "LYRIC",
            "LYRIC",
            "Well",
            "I",
            "got",
            "one",
            "foot",
            "on",
            "the",
            "platform",
            "LYRIC",
            "The",
            "other",
            "foot",
            "on",
            "the",
            "train",
            "LYRIC",
            "I’m",
            "goin’",
            "back",
            "to",
            "New",
            "Orleans",
            "LYRIC",
            "To",
            "wear",
            "that",
            "ball",
            "and",
            "chain",
            "LYRIC",
            "LYRIC",
            "Well",
            "there",
            "is",
            "a",
            "house",
            "in",
            "New",
            "Orleans",
            "LYRIC",
            "They",
            "call",
            "the",
            "Rising",
            "Sun",
            "LYRIC",
            "And",
            "it’s",
            "been",
            "the",
            "ruin",
            "of",
            "many",
            "a",
            "poor",
            "boy",
            "LYRIC",
            "And",
            "God",
            "I",
            "know",
            "I’m",
            "one"
        ]
    },
    "song_0003": {
        "tittle": "Jeremy",
        "artist": "Pearl Jam",
        "composer": "Eddie Vedder, Jeff Ament",
        "year": 1991,
        "lyrics": [
            "At",
            "home",
            "drawing",
            "pictures",
            "LYRIC",
            "Of",
            "mountain",
            "tops",
            "LYRIC",
            "With",
            "him",
            "on",
            "top",
            "LYRIC",
            "Lemon",
            "yellow",
            "sun",
            "LYRIC",
            "Arms",
            "raised",
            "in",
            "a",
            "V",
            "LYRIC",
            "Dead",
            "lay",
            "in",
            "pools",
            "of",
            "maroon",
            "below",
            "LYRIC",
            "Daddy",
            "didn’t",
            "give",
            "attention",
            "LYRIC",
            "Oh",
            "to",
            "the",
            "fact",
            "that",
            "mommy",
            "didn’t",
            "care",
            "LYRIC",
            "King",
            "Jeremy",
            "the",
            "wicked",
            "LYRIC",
            "Oh",
            "ruled",
            "his",
            "world",
            "LYRIC",
            "Jeremy",
            "spoke",
            "in",
            "class",
            "today",
            "LYRIC",
            "Jeremy",
            "spoke",
            "in",
            "class",
            "today",
            "LYRIC",
            "Clearly",
            "I",
            "remember",
            "LYRIC",
            "Pickin’",
            "on",
            "the",
            "boy",
            "LYRIC",
            "Seemed",
            "a",
            "harmless",
            "little",
            "fuck",
            "LYRIC",
            "But",
            "we",
            "unleashed",
            "the",
            "lion",
            "LYRIC",
            "Gnashed",
            "his",
            "teeth",
            "and",
            "bit",
            "the",
            "recessed",
            "lady’s",
            "breast",
            "LYRIC",
            "How",
            "could",
            "I",
            "forget",
            "LYRIC",
            "And",
            "he",
            "hit",
            "me",
            "with",
            "a",
            "surprise",
            "left",
            "LYRIC",
            "My",
            "jaw",
            "left",
            "hurting",
            "LYRIC",
            "Dropped",
            "wide",
            "open",
            "LYRIC",
            "Just",
            "like",
            "the",
            "day",
            "LYRIC",
            "Oh",
            "like",
            "the",
            "day",
            "I",
            "heard",
            "LYRIC",
            "Daddy",
            "didn’t",
            "give",
            "affection",
            "LYRIC",
            "And",
            "the",
            "boy",
            "was",
            "something",
            "that",
            "mommy",
            "wouldn’t",
            "wear",
            "LYRIC",
            "King",
            "Jeremy",
            "the",
            "wicked",
            "LYRIC",
            "Ruled",
            "his",
            "world",
            "LYRIC",
            "Jeremy",
            "spoke",
            "in",
            "class",
            "today",
            "LYRIC",
            "Jeremy",
            "spoke",
            "in",
            "class",
            "today",
            "LYRIC",
            "Jeremy",
            "spoke",
            "in",
            "class",
            "today",
            "LYRIC",
            "Try",
            "to",
            "forget",
            "this",
            "try",
            "to",
            "forget",
            "this",
            "LYRIC",
            "Try",
            "to",
            "erase",
            "this",
            "try",
            "to",
            "erase",
            "this",
            "LYRIC",
            "From",
            "the",
            "blackboard",
            "LYRIC",
            "Jeremy",
            "spoke",
            "in",
            "class",
            "today",
            "LYRIC",
            "Jeremy",
            "spoke",
            "in",
            "class",
            "today",
            "LYRIC",
            "Jeremy",
            "spoke",
            "in",
            "LYRIC",
            "Spoke",
            "in",
            "LYRIC",
            "Jeremy",
            "spoke",
            "in",
            "LYRIC",
            "Spoke",
            "in",
            "LYRIC",
            "Jeremy",
            "spoke",
            "in",
            "class",
            "today",
            "LYRIC",
            "Uh",
            "uh",
            "uh",
            "uh",
            "spoke",
            "in",
            "spoke",
            "in",
            "spoke",
            "in",
            "LYRIC",
            "Spoke",
            "in",
            "LYRIC",
            "Uh",
            "uh",
            "uh",
            "uh",
            "spoke",
            "in",
            "spoke",
            "in",
            "spoke",
            "in",
            "LYRIC",
            "Whoa",
            "oh",
            "spoke",
            "in",
            "LYRIC",
            "Spoke",
            "in",
            "spoke",
            "in",
            "LYRIC",
            "Whoa",
            "oh",
            "spoke",
            "in",
            "LYRIC",
            "Whoa",
            "oh",
            "spoke",
            "in",
            "spoke",
            "in",
            "spoke",
            "in",
            "LYRIC",
            "Ah",
            "ah",
            "ah",
            "yeah",
            "LYRIC",
            "Ah",
            "ah",
            "ah",
            "ah",
            "spoke",
            "in",
            "spoke",
            "in",
            "spoke",
            "in",
            "LYRIC",
            "Yeah",
            "yeah",
            "ah",
            "ah",
            "ah",
            "spoke",
            "in",
            "spoke",
            "in",
            "spoke",
            "in",
            "LYRIC",
            "Ah",
            "ah",
            "ah",
            "ah",
            "ah"
        ]
    },
    "song_0004": {
        "tittle": "Midnight Special",
        "artist": "Creedence Clearwater Revival",
        "composer": "Uknown",
        "year": 1967,
        "lyrics": [
            "Well",
            "you",
            "wake",
            "up",
            "in",
            "the",
            "mornin’",
            "you",
            "hear",
            "the",
            "work",
            "bell",
            "ring",
            "LYRIC",
            "And",
            "they",
            "march",
            "you",
            "to",
            "the",
            "table",
            "to",
            "see",
            "the",
            "same",
            "old",
            "thing",
            "LYRIC",
            "is",
            "no",
            "no",
            "food",
            "upon",
            "the",
            "table",
            "and",
            "no",
            "pork",
            "up",
            "in",
            "the",
            "pan",
            "LYRIC",
            "But",
            "you",
            "better",
            "not",
            "complain",
            "boy",
            "you",
            "get",
            "in",
            "trouble",
            "with",
            "the",
            "man",
            "LYRIC",
            "Let",
            "the",
            "Midnight",
            "Special",
            "shine",
            "a",
            "light",
            "on",
            "me",
            "LYRIC",
            "Let",
            "the",
            "Midnight",
            "Special",
            "shine",
            "a",
            "light",
            "on",
            "me",
            "LYRIC",
            "Let",
            "the",
            "Midnight",
            "Special",
            "shine",
            "a",
            "light",
            "on",
            "me",
            "LYRIC",
            "Let",
            "the",
            "Midnight",
            "Special",
            "shine",
            "a",
            "ever",
            "lovin’",
            "light",
            "on",
            "me",
            "LYRIC",
            "Yonder",
            "come",
            "miss",
            "Rosie",
            "how",
            "in",
            "the",
            "world",
            "did",
            "you",
            "know",
            "LYRIC",
            "By",
            "the",
            "way",
            "she",
            "wears",
            "her",
            "apron",
            "and",
            "the",
            "clothes",
            "she",
            "wore",
            "LYRIC",
            "Umbrella",
            "on",
            "her",
            "shoulder",
            "piece",
            "of",
            "paper",
            "in",
            "her",
            "hand",
            "LYRIC",
            "She",
            "come",
            "to",
            "see",
            "the",
            "gov’nor",
            "she",
            "wants",
            "to",
            "free",
            "her",
            "man",
            "LYRIC",
            "Let",
            "the",
            "Midnight",
            "Special",
            "shine",
            "a",
            "light",
            "on",
            "me",
            "LYRIC",
            "Let",
            "the",
            "Midnight",
            "Special",
            "shine",
            "a",
            "light",
            "on",
            "me",
            "LYRIC",
            "Let",
            "the",
            "Midnight",
            "Special",
            "shine",
            "a",
            "light",
            "on",
            "me",
            "LYRIC",
            "Let",
            "the",
            "Midnight",
            "Special",
            "shine",
            "a",
            "ever",
            "lovin’",
            "light",
            "on",
            "me",
            "LYRIC",
            "If",
            "you’re",
            "ever",
            "in",
            "Houston",
            "well",
            "you",
            "better",
            "do",
            "the",
            "right",
            "LYRIC",
            "You",
            "better",
            "not",
            "gamble",
            "there",
            "you",
            "better",
            "not",
            "fight",
            "at",
            "all",
            "LYRIC",
            "Or",
            "the",
            "sheriff",
            "will",
            "grab",
            "ya",
            "and",
            "the",
            "boys",
            "will",
            "bring",
            "you",
            "down",
            "LYRIC",
            "The",
            "next",
            "thing",
            "you",
            "know",
            "boy",
            "Oh",
            "You’re",
            "prison",
            "bound",
            "LYRIC",
            "Let",
            "the",
            "Midnight",
            "Special",
            "shine",
            "a",
            "light",
            "on",
            "me",
            "LYRIC",
            "Let",
            "the",
            "Midnight",
            "Special",
            "shine",
            "a",
            "light",
            "on",
            "me",
            "LYRIC",
            "Let",
            "the",
            "Midnight",
            "Special",
            "shine",
            "a",
            "light",
            "on",
            "me",
            "LYRIC",
            "Let",
            "the",
            "Midnight",
            "Special",
            "shine",
            "a",
            "ever",
            "lovin’",
            "light",
            "on",
            "me",
            "LYRIC",
            "Let",
            "the",
            "Midnight",
            "Special",
            "shine",
            "a",
            "light",
            "on",
            "me",
            "LYRIC",
            "Let",
            "the",
            "Midnight",
            "Special",
            "shine",
            "a",
            "light",
            "on",
            "me",
            "LYRIC",
            "Let",
            "the",
            "Midnight",
            "Special",
            "shine",
            "a",
            "light",
            "on",
            "me",
            "LYRIC",
            "Let",
            "the",
            "Midnight",
            "Special",
            "shine",
            "a",
            "everlovin’",
            "light",
            "on",
            "me"
        ]
    },
    "song_0005": {
        "tittle": "Lo Hi",
        "artist": "The Black Keys",
        "composer": "The Black Keys",
        "year": 2019,
        "lyrics": [
            "Out",
            "on",
            "a",
            "limb",
            "in",
            "the",
            "wind",
            "of",
            "a",
            "hurricane",
            "LYRIC",
            "Down",
            "at",
            "the",
            "bar",
            "like",
            "a",
            "star",
            "in",
            "the",
            "howling",
            "rain",
            "LYRIC",
            "LYRIC",
            "Nobody",
            "to",
            "love",
            "you",
            "LYRIC",
            "Nobody",
            "to",
            "care",
            "LYRIC",
            "If",
            "you",
            "die",
            "nobody",
            "will",
            "hug",
            "you",
            "LYRIC",
            "No",
            "one",
            "to",
            "answer",
            "your",
            "prayer",
            "LYRIC",
            "LYRIC",
            "You",
            "get",
            "low",
            "Low",
            "like",
            "a",
            "valley",
            "LYRIC",
            "You",
            "get",
            "high",
            "High",
            "like",
            "a",
            "bird",
            "in",
            "the",
            "sky",
            "LYRIC",
            "You",
            "get",
            "low",
            "Low",
            "’cause",
            "you’re",
            "angry",
            "LYRIC",
            "Low",
            "high",
            "high",
            "low",
            "LYRIC",
            "LYRIC",
            "One",
            "at",
            "a",
            "time",
            "get",
            "in",
            "line",
            "for",
            "the",
            "masquerade",
            "LYRIC",
            "Drink",
            "’til",
            "you",
            "cry",
            "and",
            "you’re",
            "lyin’",
            "in",
            "the",
            "mess",
            "you",
            "made",
            "LYRIC",
            "LYRIC",
            "Nobody",
            "to",
            "love",
            "you",
            "LYRIC",
            "Nobody",
            "to",
            "care",
            "LYRIC",
            "Nobody",
            "to",
            "drug",
            "you",
            "LYRIC",
            "No",
            "one",
            "to",
            "hold",
            "back",
            "your",
            "hair",
            "LYRIC",
            "LYRIC",
            "You",
            "get",
            "low",
            "Low",
            "like",
            "a",
            "valley",
            "LYRIC",
            "You",
            "get",
            "high",
            "High",
            "like",
            "a",
            "bird",
            "in",
            "the",
            "sky",
            "LYRIC",
            "You",
            "get",
            "low",
            "Low",
            "’cause",
            "you’re",
            "angry",
            "LYRIC",
            "Low",
            "high",
            "high",
            "low",
            "LYRIC",
            "LYRIC",
            "You",
            "get",
            "low",
            "Low",
            "like",
            "a",
            "valley",
            "LYRIC",
            "You",
            "get",
            "high",
            "High",
            "like",
            "a",
            "bird",
            "in",
            "the",
            "sky",
            "LYRIC",
            "You",
            "get",
            "low",
            "Low",
            "’cause",
            "you’re",
            "angry",
            "LYRIC",
            "Low",
            "high",
            "high",
            "low",
            "LYRIC",
            "Low",
            "high",
            "high",
            "low",
            "LYRIC",
            "Low",
            "high",
            "high",
            "low",
            "LYRIC"
        ]
    }
}